gptchatbotcli/__init__.py
gptchatbotcli/database.py
gptchatbotcli/history.py
gptchatbotcli/index.py
gptchatbotcli/openapi_controller.py
gptchatbotcli/payloads.py
gptchatbotcli/services.py
gpt_chatbot_cli-0.3.4.dist-info/LICENCE
gpt_chatbot_cli-0.3.4.dist-info/METADATA
gpt_chatbot_cli-0.3.4.dist-info/WHEEL
gpt_chatbot_cli-0.3.4.dist-info/entry_points.txt
gpt_chatbot_cli-0.3.4.dist-info/top_level.txt
gpt_chatbot_cli-0.3.4.dist-info/RECORD
