Metadata-Version: 2.1
Name: gpt-chatbot-cli
Version: 0.3.4
Summary: A minimal chatgpt cli
Author-email: Ruben Kharel <talkto@rubenk.com.np>
Project-URL: Homepage, https://github.com/slithery0/gpt-chatbot-cli
Project-URL: Bug Tracker, https://github.com/slithery0/gpt-chatbot-cli/issues
Keywords: chatgpt,gpt-chatbot,chatgpt-cli
Classifier: Development Status :: 4 - Beta
Classifier: Intended Audience :: End Users/Desktop
Classifier: License :: OSI Approved :: MIT License
Classifier: Programming Language :: Python :: 3.9
Classifier: Topic :: Text Processing :: Linguistic
Classifier: Topic :: Utilities
License-File: LICENCE
Requires-Dist: openai (==0.27.4)
Requires-Dist: prompt-toolkit (==3.0.38)
Requires-Dist: termcolor (==2.2.0)
Requires-Dist: tinydb (==4.7.1)
Requires-Dist: click (==8.1.3)
